rustc_t_x64_win_msvc_nightly_p3/__init__.py
rustc_t_x64_win_msvc_nightly_p3/data/bin/rustc.exe
rustc_t_x64_win_msvc_nightly_p3/data/bin/rustc.pdb
rustc_t_x64_win_msvc_nightly_p3/data/bin/rustc_driver-00a065e462aa96d9.pdb
rustc_t_x64_win_msvc_nightly_p3/data/lib/rustlib/etc/gdb_load_rust_pretty_printers.py
rustc_t_x64_win_msvc_nightly_p3/data/lib/rustlib/etc/gdb_lookup.py
rustc_t_x64_win_msvc_nightly_p3/data/lib/rustlib/etc/gdb_providers.py
rustc_t_x64_win_msvc_nightly_p3/data/lib/rustlib/etc/intrinsic.natvis
rustc_t_x64_win_msvc_nightly_p3/data/lib/rustlib/etc/liballoc.natvis
rustc_t_x64_win_msvc_nightly_p3/data/lib/rustlib/etc/libcore.natvis
rustc_t_x64_win_msvc_nightly_p3/data/lib/rustlib/etc/libstd.natvis
rustc_t_x64_win_msvc_nightly_p3/data/lib/rustlib/etc/lldb_commands
rustc_t_x64_win_msvc_nightly_p3/data/lib/rustlib/etc/lldb_lookup.py
rustc_t_x64_win_msvc_nightly_p3/data/lib/rustlib/etc/lldb_providers.py
rustc_t_x64_win_msvc_nightly_p3/data/lib/rustlib/etc/rust_types.py
rustc_t_x64_win_msvc_nightly_p3/data/lib/rustlib/x86_64-pc-windows-msvc/bin/gcc-ld/ld.lld.exe
rustc_t_x64_win_msvc_nightly_p3/data/lib/rustlib/x86_64-pc-windows-msvc/bin/gcc-ld/ld.lld.pdb
rustc_t_x64_win_msvc_nightly_p3/data/lib/rustlib/x86_64-pc-windows-msvc/bin/gcc-ld/ld64.lld.exe
rustc_t_x64_win_msvc_nightly_p3/data/lib/rustlib/x86_64-pc-windows-msvc/bin/gcc-ld/ld64.lld.pdb
rustc_t_x64_win_msvc_nightly_p3/data/lib/rustlib/x86_64-pc-windows-msvc/bin/gcc-ld/lld-link.exe
rustc_t_x64_win_msvc_nightly_p3/data/lib/rustlib/x86_64-pc-windows-msvc/bin/gcc-ld/lld-link.pdb
rustc_t_x64_win_msvc_nightly_p3/data/lib/rustlib/x86_64-pc-windows-msvc/bin/gcc-ld/wasm-ld.exe
rustc_t_x64_win_msvc_nightly_p3/data/lib/rustlib/x86_64-pc-windows-msvc/bin/gcc-ld/wasm-ld.pdb
rustc_t_x64_win_msvc_nightly_p3/data/libexec/rust-analyzer-proc-macro-srv.exe
rustc_t_x64_win_msvc_nightly_p3/data/libexec/rust-analyzer-proc-macro-srv.pdb
rustc_t_x64_win_msvc_nightly_p3-1.91.0.dist-info/METADATA
rustc_t_x64_win_msvc_nightly_p3-1.91.0.dist-info/WHEEL
rustc_t_x64_win_msvc_nightly_p3-1.91.0.dist-info/top_level.txt
rustc_t_x64_win_msvc_nightly_p3-1.91.0.dist-info/RECORD
